{
  "media": [
    {
      "src": "./assets/pics/2024/nature-de-luxe/ansichten/_MG_3875_(c)_martin_grabner.jpg",
      "alt": "Ansicht der Ausstellung Nature de Luxe",
      "caption": "Ausstellung Nature de Luxe, Foto: © Martin Grabner"
    },
    {
      "src": "./assets/pics/2024/nature-de-luxe/ansichten/_MG_3877_(c)_martin_grabner.jpg",
      "alt": "Ansicht der Ausstellung Nature de Luxe",
      "caption": "Ausstellung Nature de Luxe, Foto: © Martin Grabner"
    },
    {
      "src": "./assets/pics/2024/nature-de-luxe/ansichten/_MG_3878_(c)_martin_grabner.jpg",
      "alt": "Ansicht der Ausstellung Nature de Luxe",
      "caption": "Ausstellung Nature de Luxe, Foto: © Martin Grabner"
    },
    {
      "src": "./assets/pics/2024/nature-de-luxe/ansichten/_MG_3879_(c)_martin_grabner.jpg",
      "alt": "Ansicht der Ausstellung Nature de Luxe",
      "caption": "Ausstellung Nature de Luxe, Foto: © Martin Grabner"
    },
    {
      "src": "./assets/pics/2024/nature-de-luxe/ansichten/_MG_3881_(c)_martin_grabner.jpg",
      "alt": "Ansicht der Ausstellung Nature de Luxe",
      "caption": "Ausstellung Nature de Luxe, Foto: © Martin Grabner"
    },
    {
      "src": "./assets/pics/2024/nature-de-luxe/ansichten/_MG_3883_(c)_martin_grabner.jpg",
      "alt": "Ansicht der Ausstellung Nature de Luxe",
      "caption": "Ausstellung Nature de Luxe, Foto: © Martin Grabner"
    },
    {
      "src": "./assets/pics/2024/nature-de-luxe/ansichten/_MG_3885_(c)_martin_grabner.jpg",
      "alt": "Ansicht der Ausstellung Nature de Luxe",
      "caption": "Ausstellung Nature de Luxe, Foto: © Martin Grabner"
    },
    {
      "src": "./assets/pics/2024/nature-de-luxe/ansichten/_MG_3886_(c)_martin_grabner.jpg",
      "alt": "Ansicht der Ausstellung Nature de Luxe",
      "caption": "Ausstellung Nature de Luxe, Foto: © Martin Grabner"
    },
    {
      "src": "./assets/pics/2024/nature-de-luxe/ansichten/_MG_3887_(c)_martin_grabner.jpg",
      "alt": "Ansicht der Ausstellung Nature de Luxe",
      "caption": "Ausstellung Nature de Luxe, Foto: © Martin Grabner"
    },
    {
      "src": "./assets/pics/2024/nature-de-luxe/ansichten/_MG_3888_(c)_martin_grabner.jpg",
      "alt": "Ansicht der Ausstellung Nature de Luxe",
      "caption": "Ausstellung Nature de Luxe, Foto: © Martin Grabner"
    },
    {
      "src": "./assets/pics/2024/nature-de-luxe/ansichten/_MG_3889_(c)_martin_grabner.jpg",
      "alt": "Ansicht der Ausstellung Nature de Luxe",
      "caption": "Ausstellung Nature de Luxe, Foto: © Martin Grabner"
    },
    {
      "src": "./assets/pics/2024/nature-de-luxe/ansichten/_MG_3892_(c)_martin_grabner.jpg",
      "alt": "Ansicht der Ausstellung Nature de Luxe",
      "caption": "Ausstellung Nature de Luxe, Foto: © Martin Grabner"
    },
    {
      "src": "./assets/pics/2024/nature-de-luxe/ansichten/_MG_3895_(c)_martin_grabner.jpg",
      "alt": "Ansicht der Ausstellung Nature de Luxe",
      "caption": "Ausstellung Nature de Luxe, Foto: © Martin Grabner"
    },
    {
      "src": "./assets/pics/2024/nature-de-luxe/ansichten/_MG_3896_(c)_martin_grabner.jpg",
      "alt": "Ansicht der Ausstellung Nature de Luxe",
      "caption": "Ausstellung Nature de Luxe, Foto: © Martin Grabner"
    },
    {
      "src": "./assets/pics/2024/nature-de-luxe/ansichten/_MG_3897_(c)_martin_grabner.jpg",
      "alt": "Ansicht der Ausstellung Nature de Luxe",
      "caption": "Ausstellung Nature de Luxe, Foto: © Martin Grabner"
    },
    {
      "src": "./assets/pics/2024/nature-de-luxe/ansichten/_MG_3898_(c)_martin_grabner.jpg",
      "alt": "Ansicht der Ausstellung Nature de Luxe",
      "caption": "Ausstellung Nature de Luxe, Foto: © Martin Grabner"
    },
    {
      "src": "./assets/pics/2024/nature-de-luxe/ansichten/_MG_3900_(c)_martin_grabner.jpg",
      "alt": "Ansicht der Ausstellung Nature de Luxe",
      "caption": "Ausstellung Nature de Luxe, Foto: © Martin Grabner"
    }
  ]
}
